gr8tool/__init__.py
gr8tool/gr8tool.py
gr8tool-0.1.9.dist-info/METADATA
gr8tool-0.1.9.dist-info/WHEEL
gr8tool-0.1.9.dist-info/top_level.txt
gr8tool-0.1.9.dist-info/RECORD
