Metadata-Version: 2.4
Name: gr8tool
Version: 0.1.9
Summary: A grading tool for tutors of the university of Freiburg for EidP.
Requires-Python: >=3.12
